ultrasound_processing/__init__.py
ultrasound_processing/masking.py
ultrasound_processing/transform.py
ultrasound_processing/transform_back.py
ultrasound_processing/data/cropped_frame_idx_100.png
ultrasound_processing/data/cropped_frame_idx_150.png
ultrasound_processing/data/cropped_frame_idx_250.png
ultrasound_processing/data/cropped_frame_idx_50.png
ultrasound_processing_package_minimal-0.2.2.dist-info/METADATA
ultrasound_processing_package_minimal-0.2.2.dist-info/WHEEL
ultrasound_processing_package_minimal-0.2.2.dist-info/top_level.txt
ultrasound_processing_package_minimal-0.2.2.dist-info/RECORD
